LICENSE
README.rst
setup.py
o3soil/__about__.py
o3soil/__init__.py
o3soil/backbone.py
o3soil/generic.py
o3soil.egg-info/PKG-INFO
o3soil.egg-info/SOURCES.txt
o3soil.egg-info/dependency_links.txt
o3soil.egg-info/not-zip-safe
o3soil.egg-info/requires.txt
o3soil.egg-info/top_level.txt
o3soil/drivers/__init__.py
o3soil/drivers/two_d.py
o3soil/drivers/n2d/__init__.py
o3soil/drivers/n2d/custom_2d.py
o3soil/drivers/n2d/ud_cdss_2d.py
o3soil/drivers/n2d/vload_2d.py
o3soil/drivers/n3d/__init__.py
o3soil/drivers/n3d/custom_3d.py
o3soil/drivers/n3d/vload_3d.py
o3soil/sra/__init__.py
o3soil/sra/one_d.py
o3soil/sra/one_d_eff.py
o3soil/sra/one_d_works.py
o3soil/sra/output.py
o3soil/ssi/__init__.py
o3soil/ssi/bnwf.py