Metadata-Version: 2.1
Name: o3soil
Version: 0.0.7
Summary: A toolkit of extensions for using o3seespy for geotechnical simulations
Home-page: UNKNOWN
Author: Maxim Millen
Author-email: maxim.millen@canterbury.ac.nz
License: MIT with OpenSees License
Platform: UNKNOWN
Classifier: Development Status :: 3 - Alpha
Classifier: Intended Audience :: Science/Research
Classifier: Topic :: Scientific/Engineering
Classifier: Programming Language :: Python :: 3
Requires-Python: >=3
Provides-Extra: test
License-File: LICENSE
